{
    "layerId": 165,
    "name": "Autonomous Editorial Governance",
    "version": "1.0.0",
    "enabled": true,
    "policies": {
        "minimumQuality": 70,
        "minimumTrust": 0.6,
        "minimumEvidence": 60,
        "maximumBias": 0.4,
        "maximumDisinfoRisk": 0.5
    },
    "violationTypes": {
        "quality": "Quality Standards Violation",
        "trust": "Trust Threshold Not Met",
        "evidence": "Insufficient Evidence",
        "bias": "Excessive Bias Detected",
        "disinformation": "Disinformation Risk",
        "viral": "Viral Manipulation Detected"
    },
    "actions": {
        "approve": "Auto-Approve",
        "review": "Manual Review Required",
        "reject": "Auto-Reject",
        "quarantine": "Quarantine"
    },
    "intervals": {
        "complianceCheck": 5000,
        "analyticsUpdate": 30000
    }
}